[
  {
    "keyword": "Feature",
    "name": "Login no Backoffice",
    "line": 1,
    "id": "login-no-backoffice",
    "tags": [],
    "uri": "login.feature",
    "elements": [
      {
        "id": "login-no-backoffice;verifica-login-invalido",
        "keyword": "Scenario",
        "line": 3,
        "name": "Verifica login invalido",
        "tags": [],
        "type": "scenario",
        "steps": [
          {
            "arguments": [],
            "keyword": "Given ",
            "line": 4,
            "name": "acesso o site backoffice",
            "result": {
              "status": "undefined",
              "duration": 80000000
            }
          },
          {
            "arguments": [],
            "keyword": "When ",
            "line": 5,
            "name": "digito um email invalido",
            "result": {
              "status": "skipped"
            }
          },
          {
            "arguments": [],
            "keyword": "Then ",
            "line": 6,
            "name": "devo visualizar mensagem de login incorreto",
            "result": {
              "status": "skipped"
            }
          }
        ]
      }
    ]
  }
]